{
    "RqUID": "testsomehing",
    "Type": "AutoOnline",
    "SourceSystem": "ALLUR",
    "Language": "test",
    "Request": {
        "Credit": {
            "CarCost": 15000000,
            "CreditTerm": 84,
            "ProductCode": "060",
            "SchemeOfFinance": "2",
            "PaymentType": "2",
            "Insurance": {
                "IsNSInsurance": true,
                "NsProductCode": "201",
                "NsCompanyCode": "006",
                "IsKasko": true,
                "KaskoProductCode": "113",
                "KaskoCompanyCode": "009",
                "IsInsuranceInside": true
            }
        },
        "Car": {
            "Brand": "Chevrolet",
            "Model": "Chevrolet-Cobalt",
            "YearNumber": 2022,
            "VINCode": "testVIN"
        },
        "Customer": {
            "IIN": "000617550816",
            "Phone": "77786581285",
            "Docs": {
                "Photo": {
                    "FileBase64Code": "Photo",
                    "FileExtension": "pdf"
                },
                "Agreement": {
                    "FileBase64Code": "Agreement",
                    "FileExtension": "pdf"
                },
                "IdentityDocument_Front": {
                    "FileBase64Code": "IdentityDocument_Front",
                    "FileExtension": "png"
                },
                "IdentityDocument_Back": {
                    "FileBase64Code": "IdentityDocument_Back",
                    "FileExtension": "png"
                }
            }
        },
        "WorkPlace": {
            "TypeActivity": "test",
            "CompanyFullName": "Prime Source",
            "JobCategory": "Development",
            "JobTitle": "Fico-developer",
            "EmploymentStatus": "full",
            "FullExperienceTerm": 74,
            "LastExperienceTerm": 12,
            "AddWorkTypeActivity": "test2",
            "MainSalary": 750000,
            "TotalSalary": 750000
        },
        "FirstAddPerson": {
            "MobilePhone": "77075738176",
            "CustomerRelation": "self"
        },
        "SecondAddPerson": {
            "MobilePhone": "77075738176",
            "CustomerRelation": "self2"
        },
        "SmsId": "1",
        "PartnerAppId": "string"
    }
}